suss/__init__.py
suss/__main__.py
suss/agent.py
suss/index.py
suss/suss.py
suss/constants/__init__.py
suss/constants/agent.py
suss/constants/boilerplate.py
suss/constants/languages.py
suss/tools/__init__.py
suss/tools/find_bugs.py
suss/tools/glob_files.py
suss/tools/grep_code.py
suss/tools/read_file.py
suss-1.0.1.dist-info/licenses/LICENSE
suss-1.0.1.dist-info/METADATA
suss-1.0.1.dist-info/WHEEL
suss-1.0.1.dist-info/entry_points.txt
suss-1.0.1.dist-info/top_level.txt
suss-1.0.1.dist-info/RECORD
