Metadata-Version: 2.4
Name: suss
Version: 1.0.1
Summary: AI-powered bug finder that knows your codebase
Requires-Python: >=3.11
License-File: LICENSE
Requires-Dist: cohere>=5.14.0
Requires-Dist: json-repair>=0.38.0
Requires-Dist: litellm==1.61.19
Requires-Dist: rich>=13.9.4
Requires-Dist: saplings>=6.0.0
Requires-Dist: sortedcollections>=2.1.0
Requires-Dist: tree-sitter>=0.24.0
Requires-Dist: tree-sitter-language-pack>=0.7.2
Dynamic: license-file
